{"nodes": [{"id": "c_users_alfamas_desktop_zeroauth_packages_ui_src_app_admin_workload_page_tsx", "label": "page.tsx", "file_type": "code", "source_file": "C:\\Users\\ALFAMAS\\Desktop\\zeroauth\\packages\\ui\\src\\app\\admin\\workload\\page.tsx", "source_location": "L1"}, {"id": "workload_page_createdcredential", "label": "CreatedCredential", "file_type": "code", "source_file": "C:\\Users\\ALFAMAS\\Desktop\\zeroauth\\packages\\ui\\src\\app\\admin\\workload\\page.tsx", "source_location": "L9"}, {"id": "workload_page_workloadcredential", "label": "WorkloadCredential", "file_type": "code", "source_file": "C:\\Users\\ALFAMAS\\Desktop\\zeroauth\\packages\\ui\\src\\app\\admin\\workload\\page.tsx", "source_location": "L17"}, {"id": "workload_page_cred_status_styles", "label": "CRED_STATUS_STYLES", "file_type": "code", "source_file": "C:\\Users\\ALFAMAS\\Desktop\\zeroauth\\packages\\ui\\src\\app\\admin\\workload\\page.tsx", "source_location": "L28"}, {"id": "workload_page_issuedtoken", "label": "IssuedToken", "file_type": "code", "source_file": "C:\\Users\\ALFAMAS\\Desktop\\zeroauth\\packages\\ui\\src\\app\\admin\\workload\\page.tsx", "source_location": "L34"}, {"id": "workload_page_copybutton", "label": "CopyButton()", "file_type": "code", "source_file": "C:\\Users\\ALFAMAS\\Desktop\\zeroauth\\packages\\ui\\src\\app\\admin\\workload\\page.tsx", "source_location": "L43"}, {"id": "workload_page_adminworkloadpage", "label": "AdminWorkloadPage()", "file_type": "code", "source_file": "C:\\Users\\ALFAMAS\\Desktop\\zeroauth\\packages\\ui\\src\\app\\admin\\workload\\page.tsx", "source_location": "L60"}], "edges": [{"source": "c_users_alfamas_desktop_zeroauth_packages_ui_src_app_admin_workload_page_tsx", "target": "react", "relation": "imports_from", "context": "import", "confidence": "EXTRACTED", "source_file": "C:\\Users\\ALFAMAS\\Desktop\\zeroauth\\packages\\ui\\src\\app\\admin\\workload\\page.tsx", "source_location": "L3", "weight": 1.0}, {"source": "c_users_alfamas_desktop_zeroauth_packages_ui_src_app_admin_workload_page_tsx", "target": "lucide_react", "relation": "imports_from", "context": "import", "confidence": "EXTRACTED", "source_file": "C:\\Users\\ALFAMAS\\Desktop\\zeroauth\\packages\\ui\\src\\app\\admin\\workload\\page.tsx", "source_location": "L4", "weight": 1.0}, {"source": "c_users_alfamas_desktop_zeroauth_packages_ui_src_app_admin_workload_page_tsx", "target": "c_users_alfamas_desktop_zeroauth_packages_ui_src_lib_api_ts", "relation": "imports_from", "context": "import", "confidence": "EXTRACTED", "source_file": "C:\\Users\\ALFAMAS\\Desktop\\zeroauth\\packages\\ui\\src\\app\\admin\\workload\\page.tsx", "source_location": "L5", "weight": 1.0}, {"source": "c_users_alfamas_desktop_zeroauth_packages_ui_src_app_admin_workload_page_tsx", "target": "lib_api_api", "relation": "imports", "context": "import", "confidence": "EXTRACTED", "source_file": "C:\\Users\\ALFAMAS\\Desktop\\zeroauth\\packages\\ui\\src\\app\\admin\\workload\\page.tsx", "source_location": "L5", "weight": 1.0}, {"source": "c_users_alfamas_desktop_zeroauth_packages_ui_src_app_admin_workload_page_tsx", "target": "workload_page_createdcredential", "relation": "contains", "confidence": "EXTRACTED", "source_file": "C:\\Users\\ALFAMAS\\Desktop\\zeroauth\\packages\\ui\\src\\app\\admin\\workload\\page.tsx", "source_location": "L9", "weight": 1.0}, {"source": "c_users_alfamas_desktop_zeroauth_packages_ui_src_app_admin_workload_page_tsx", "target": "workload_page_workloadcredential", "relation": "contains", "confidence": "EXTRACTED", "source_file": "C:\\Users\\ALFAMAS\\Desktop\\zeroauth\\packages\\ui\\src\\app\\admin\\workload\\page.tsx", "source_location": "L17", "weight": 1.0}, {"source": "c_users_alfamas_desktop_zeroauth_packages_ui_src_app_admin_workload_page_tsx", "target": "workload_page_cred_status_styles", "relation": "contains", "confidence": "EXTRACTED", "source_file": "C:\\Users\\ALFAMAS\\Desktop\\zeroauth\\packages\\ui\\src\\app\\admin\\workload\\page.tsx", "source_location": "L28", "weight": 1.0}, {"source": "c_users_alfamas_desktop_zeroauth_packages_ui_src_app_admin_workload_page_tsx", "target": "workload_page_issuedtoken", "relation": "contains", "confidence": "EXTRACTED", "source_file": "C:\\Users\\ALFAMAS\\Desktop\\zeroauth\\packages\\ui\\src\\app\\admin\\workload\\page.tsx", "source_location": "L34", "weight": 1.0}, {"source": "c_users_alfamas_desktop_zeroauth_packages_ui_src_app_admin_workload_page_tsx", "target": "workload_page_copybutton", "relation": "contains", "confidence": "EXTRACTED", "source_file": "C:\\Users\\ALFAMAS\\Desktop\\zeroauth\\packages\\ui\\src\\app\\admin\\workload\\page.tsx", "source_location": "L43", "weight": 1.0}, {"source": "c_users_alfamas_desktop_zeroauth_packages_ui_src_app_admin_workload_page_tsx", "target": "workload_page_adminworkloadpage", "relation": "contains", "confidence": "EXTRACTED", "source_file": "C:\\Users\\ALFAMAS\\Desktop\\zeroauth\\packages\\ui\\src\\app\\admin\\workload\\page.tsx", "source_location": "L60", "weight": 1.0}], "raw_calls": [{"caller_nid": "workload_page_copybutton", "callee": "useState", "is_member_call": false, "source_file": "C:\\Users\\ALFAMAS\\Desktop\\zeroauth\\packages\\ui\\src\\app\\admin\\workload\\page.tsx", "source_location": "L44"}, {"caller_nid": "workload_page_adminworkloadpage", "callee": "useState", "is_member_call": false, "source_file": "C:\\Users\\ALFAMAS\\Desktop\\zeroauth\\packages\\ui\\src\\app\\admin\\workload\\page.tsx", "source_location": "L62"}, {"caller_nid": "workload_page_adminworkloadpage", "callee": "useState", "is_member_call": false, "source_file": "C:\\Users\\ALFAMAS\\Desktop\\zeroauth\\packages\\ui\\src\\app\\admin\\workload\\page.tsx", "source_location": "L63"}, {"caller_nid": "workload_page_adminworkloadpage", "callee": "useState", "is_member_call": false, "source_file": "C:\\Users\\ALFAMAS\\Desktop\\zeroauth\\packages\\ui\\src\\app\\admin\\workload\\page.tsx", "source_location": "L64"}, {"caller_nid": "workload_page_adminworkloadpage", "callee": "useState", "is_member_call": false, "source_file": "C:\\Users\\ALFAMAS\\Desktop\\zeroauth\\packages\\ui\\src\\app\\admin\\workload\\page.tsx", "source_location": "L65"}, {"caller_nid": "workload_page_adminworkloadpage", "callee": "useState", "is_member_call": false, "source_file": "C:\\Users\\ALFAMAS\\Desktop\\zeroauth\\packages\\ui\\src\\app\\admin\\workload\\page.tsx", "source_location": "L66"}, {"caller_nid": "workload_page_adminworkloadpage", "callee": "useState", "is_member_call": false, "source_file": "C:\\Users\\ALFAMAS\\Desktop\\zeroauth\\packages\\ui\\src\\app\\admin\\workload\\page.tsx", "source_location": "L69"}, {"caller_nid": "workload_page_adminworkloadpage", "callee": "useState", "is_member_call": false, "source_file": "C:\\Users\\ALFAMAS\\Desktop\\zeroauth\\packages\\ui\\src\\app\\admin\\workload\\page.tsx", "source_location": "L70"}, {"caller_nid": "workload_page_adminworkloadpage", "callee": "useState", "is_member_call": false, "source_file": "C:\\Users\\ALFAMAS\\Desktop\\zeroauth\\packages\\ui\\src\\app\\admin\\workload\\page.tsx", "source_location": "L71"}, {"caller_nid": "workload_page_adminworkloadpage", "callee": "useState", "is_member_call": false, "source_file": "C:\\Users\\ALFAMAS\\Desktop\\zeroauth\\packages\\ui\\src\\app\\admin\\workload\\page.tsx", "source_location": "L72"}, {"caller_nid": "workload_page_adminworkloadpage", "callee": "useState", "is_member_call": false, "source_file": "C:\\Users\\ALFAMAS\\Desktop\\zeroauth\\packages\\ui\\src\\app\\admin\\workload\\page.tsx", "source_location": "L75"}, {"caller_nid": "workload_page_adminworkloadpage", "callee": "useState", "is_member_call": false, "source_file": "C:\\Users\\ALFAMAS\\Desktop\\zeroauth\\packages\\ui\\src\\app\\admin\\workload\\page.tsx", "source_location": "L76"}, {"caller_nid": "workload_page_adminworkloadpage", "callee": "useState", "is_member_call": false, "source_file": "C:\\Users\\ALFAMAS\\Desktop\\zeroauth\\packages\\ui\\src\\app\\admin\\workload\\page.tsx", "source_location": "L77"}, {"caller_nid": "workload_page_adminworkloadpage", "callee": "useEffect", "is_member_call": false, "source_file": "C:\\Users\\ALFAMAS\\Desktop\\zeroauth\\packages\\ui\\src\\app\\admin\\workload\\page.tsx", "source_location": "L90"}, {"caller_nid": "workload_page_adminworkloadpage", "callee": "toLocaleString", "is_member_call": true, "source_file": "C:\\Users\\ALFAMAS\\Desktop\\zeroauth\\packages\\ui\\src\\app\\admin\\workload\\page.tsx", "source_location": "L267"}, {"caller_nid": "workload_page_adminworkloadpage", "callee": "map", "is_member_call": true, "source_file": "C:\\Users\\ALFAMAS\\Desktop\\zeroauth\\packages\\ui\\src\\app\\admin\\workload\\page.tsx", "source_location": "L341"}, {"caller_nid": "workload_page_adminworkloadpage", "callee": "map", "is_member_call": true, "source_file": "C:\\Users\\ALFAMAS\\Desktop\\zeroauth\\packages\\ui\\src\\app\\admin\\workload\\page.tsx", "source_location": "L366"}]}